_oxyde_core/__init__.py
_oxyde_core/_oxyde_core.cpython-311-darwin.so
oxyde_core-0.3.0.dist-info/METADATA
oxyde_core-0.3.0.dist-info/WHEEL
oxyde_core-0.3.0.dist-info/RECORD
