Metadata-Version: 2.4
Name: oxyde-core
Version: 0.3.0
Classifier: Development Status :: 4 - Beta
Classifier: Intended Audience :: Developers
Classifier: License :: OSI Approved :: MIT License
Classifier: Programming Language :: Rust
Classifier: Programming Language :: Python :: Implementation :: CPython
Classifier: Programming Language :: Python :: 3
Classifier: Programming Language :: Python :: 3.10
Classifier: Programming Language :: Python :: 3.11
Classifier: Programming Language :: Python :: 3.12
Classifier: Programming Language :: Python :: 3.13
Classifier: Programming Language :: Python :: 3.14
Classifier: Topic :: Database
Summary: Rust core for Oxyde ORM - high-performance database operations
Keywords: orm,rust,database,async,performance
Author-email: Nikita Ryzhenkov <nikita.ryzhenkoff@gmail.com>
License: MIT
Requires-Python: >=3.10
Project-URL: Homepage, https://github.com/mr-fatalyst/oxyde
Project-URL: Documentation, https://github.com/mr-fatalyst/oxyde#readme
Project-URL: Repository, https://github.com/mr-fatalyst/oxyde
Project-URL: Issues, https://github.com/mr-fatalyst/oxyde/issues
